luftdaten/__init__.py
luftdaten/exceptions.py
luftdaten-0.7.3.dist-info/LICENSE
luftdaten-0.7.3.dist-info/WHEEL
luftdaten-0.7.3.dist-info/METADATA
luftdaten-0.7.3.dist-info/RECORD
