Metadata-Version: 2.1
Name: luftdaten
Version: 0.7.3
Summary: Python API for interacting with luftdaten.info
Home-page: https://github.com/home-assistant-ecosystem/python-luftdaten
License: MIT
Author: Fabian Affolter
Author-email: mail@fabian-affolter.ch
Requires-Python: >=3.9,<4.0
Classifier: Development Status :: 3 - Alpha
Classifier: Environment :: Console
Classifier: Intended Audience :: Developers
Classifier: License :: OSI Approved :: MIT License
Classifier: Operating System :: MacOS :: MacOS X
Classifier: Operating System :: Microsoft :: Windows
Classifier: Operating System :: POSIX
Classifier: Programming Language :: Python :: 3
Classifier: Programming Language :: Python :: 3.10
Classifier: Programming Language :: Python :: 3.9
Classifier: Topic :: Home Automation
Classifier: Topic :: Utilities
Requires-Dist: httpx (>=0.23,<1)
Project-URL: Repository, https://github.com/home-assistant-ecosystem/python-luftdaten
